untappd_crawler/__init__.py
untappd_crawler/beer.py
untappd_crawler/user.py
untappd_crawler-0.2.data/scripts/untappd_crawler
untappd_crawler-0.2.dist-info/DESCRIPTION.rst
untappd_crawler-0.2.dist-info/METADATA
untappd_crawler-0.2.dist-info/RECORD
untappd_crawler-0.2.dist-info/WHEEL
untappd_crawler-0.2.dist-info/metadata.json
untappd_crawler-0.2.dist-info/top_level.txt
