Metadata-Version: 2.0
Name: untappd-crawler
Version: 0.2
Summary: A CLI client for exporting elasticsearch data to csv
Home-page: https://github.com/therako/untappd_crawler
Author: Arun Kumar Ramanathan
Author-email: rako.aka.arun@gmail.com
License: MIT License
Platform: UNKNOWN
Classifier: License :: OSI Approved :: MIT License
Classifier: Development Status :: 3 - Alpha
Classifier: Operating System :: OS Independent
Classifier: Programming Language :: Python
Classifier: Programming Language :: Python :: 2
Classifier: Programming Language :: Python :: 2.7
